setup.py
python_colorful_font_output/__init__.py
python_colorful_font_output/colorful_output.py
python_colorful_font_output/informationlib.py
python_colorful_font_output.egg-info/PKG-INFO
python_colorful_font_output.egg-info/SOURCES.txt
python_colorful_font_output.egg-info/dependency_links.txt
python_colorful_font_output.egg-info/top_level.txt