Metadata-Version: 2.1
Name: python-colorful-font-output
Version: 1.0.2
Summary: This is a library to make your terminal much beautiful! 
Home-page: https://github.com/
Author: Yuli Wang
Author-email: winterland_yuli2@163.com
License: UNKNOWN
Platform: UNKNOWN
Classifier: Programming Language :: Python :: 3
Classifier: License :: OSI Approved :: MIT License
Classifier: Operating System :: OS Independent
